pypomes_iam/__init__.py
pypomes_iam/iam_actions.py
pypomes_iam/iam_common.py
pypomes_iam/iam_pomes.py
pypomes_iam/iam_services.py
pypomes_iam/provider_pomes.py
pypomes_iam-1.0.7.dist-info/METADATA
pypomes_iam-1.0.7.dist-info/WHEEL
pypomes_iam-1.0.7.dist-info/licenses/LICENSE
pypomes_iam-1.0.7.dist-info/RECORD
