Metadata-Version: 2.4
Name: pypomes_iam
Version: 1.0.7
Summary: A collection of Python pomes, penyeach (IAM modules)
Project-URL: Homepage, https://github.com/TheWiseCoder/PyPomes-IAM
Project-URL: Bug Tracker, https://github.com/TheWiseCoder/PyPomes-IAM/issues
Author-email: GT Nunes <wisecoder01@gmail.com>
License-File: LICENSE
Classifier: License :: OSI Approved :: MIT License
Classifier: Operating System :: OS Independent
Classifier: Programming Language :: Python :: 3
Requires-Python: >=3.14
Requires-Dist: flask>=3.1.2
Requires-Dist: pyjwt>=2.10.1
Requires-Dist: pypomes-core>=2.9.4
Requires-Dist: pypomes-crypto>=0.8.6
Requires-Dist: requests>=2.32.5
